sardine_web/__init__.py
sardine_web/client/dist/index.html
sardine_web/client/dist/assets/DroidSansMono-webfont-81df918e.woff
sardine_web/client/dist/assets/FiraCode-Bold-cb8eb487.ttf
sardine_web/client/dist/assets/FiraCode-Light-9a0ab96c.ttf
sardine_web/client/dist/assets/FiraCode-Regular-d6641a9a.ttf
sardine_web/client/dist/assets/FiraCode-SemiBold-acc523d8.ttf
sardine_web/client/dist/assets/SpaceMono-Regular-74ea8049.ttf
sardine_web/client/dist/assets/fa-solid-900-67a65763.ttf
sardine_web/client/dist/assets/fa-solid-900-7152a693.woff2
sardine_web/client/dist/assets/index-6b99a904.js
sardine_web/client/dist/assets/index-a0721fe6.css
sardine_web/client/dist/assets/jgs5-0e03e537.woff2
sardine_web/client/dist/assets/jgs5-9f26a38a.woff
sardine_web/client/dist/assets/jgs7-a69a9a5d.woff2
sardine_web/client/dist/assets/jgs7-d3f51478.woff
sardine_web/client/dist/assets/jgs9-0c41ef37.woff
sardine_web/client/dist/assets/jgs9-dc75d6ab.woff2
sardine_web/client/dist/assets/unifont-12.0.01-7c52c0bf.woff2
sardine_web/client/dist/assets/unifont_upper-12.0.01-01155c4f.woff2
sardine_web/server/__init__.py
sardine_web/server/flask_server.py
sardine_web-1.1.0.dist-info/LICENSE.txt
sardine_web-1.1.0.dist-info/METADATA
sardine_web-1.1.0.dist-info/WHEEL
sardine_web-1.1.0.dist-info/entry_points.txt
sardine_web-1.1.0.dist-info/top_level.txt
sardine_web-1.1.0.dist-info/RECORD
