Metadata-Version: 2.1
Name: sardine-web
Version: 1.1.0
Summary: Official web editor plugin for sardine-system
Author: Raphaël Forment, thegamecracks
Author-email: raphael.forment@gmail.com
License: GPL-3.0-only
Project-URL: Homepage, https://sardine.raphaelforment.fr
Project-URL: Documentation, https://sardine.raphaelforment.fr
Project-URL: Source Code, https://github.com/sardine-system/sardine-web
Project-URL: Bug Tracker, https://github.com/sardine-system/sardine-web/issues
Keywords: algorave,live-coding,music,patterns
Classifier: Development Status :: 5 - Production/Stable
Classifier: Framework :: Flask
Classifier: Intended Audience :: End Users/Desktop
Classifier: Intended Audience :: Science/Research
Classifier: License :: OSI Approved
Classifier: License :: OSI Approved :: GNU General Public License v3 (GPLv3)
Classifier: Programming Language :: Python
Classifier: Programming Language :: Python :: 3
Classifier: Programming Language :: Python :: 3.10
Classifier: Programming Language :: Python :: 3.11
Classifier: Topic :: Artistic Software
Classifier: Topic :: Multimedia
Classifier: Topic :: Multimedia :: Sound/Audio
Classifier: Topic :: Multimedia :: Sound/Audio :: MIDI
Requires-Python: >=3.10
License-File: LICENSE.txt
Requires-Dist: appdirs (>=1.4)
Requires-Dist: click (>=8.1.3)
Requires-Dist: Flask-SocketIO (>=5.3.2)
Requires-Dist: Flask-Cors (>=3.0)
Requires-Dist: Flask (>=2.2.2)
Requires-Dist: pygtail (>=0.14.0)
Requires-Dist: rich (>=12.5)
Requires-Dist: sardine-system (>=0.4.0)
Provides-Extra: dev
Requires-Dist: black (>=22.8) ; extra == 'dev'
